{
  "name": "Umi測試2",
  "saved_at": "2026-04-18 09:14:21",
  "events": [
    {
      "type": "press",
      "button": "ctrl",
      "at": 3.56,
      "at_jitter": 0.0,
      "at_random_sec": 0.25,
      "buff_group": "",
      "buff_cycle_sec": 0.0,
      "buff_jitter_sec": 0.0,
      "replicatedRow": 0,
      "row_color": ""
    },
    {
      "type": "release",
      "button": "ctrl",
      "at": 3.69,
      "at_jitter": 0.0,
      "at_random_sec": 0.25,
      "buff_group": "",
      "buff_cycle_sec": 0.0,
      "buff_jitter_sec": 0.0,
      "replicatedRow": 0,
      "row_color": ""
    },
    {
      "type": "press",
      "button": "shift",
      "at": 6.73,
      "at_jitter": 0.0,
      "at_random_sec": 0.25,
      "buff_group": "",
      "buff_cycle_sec": 0.0,
      "buff_jitter_sec": 0.0,
      "replicatedRow": 0,
      "row_color": ""
    },
    {
      "type": "release",
      "button": "shift",
      "at": 6.77,
      "at_jitter": 0.0,
      "at_random_sec": 0.25,
      "buff_group": "",
      "buff_cycle_sec": 0.0,
      "buff_jitter_sec": 0.0,
      "replicatedRow": 0,
      "row_color": ""
    },
    {
      "type": "press",
      "button": "shift",
      "at": 6.99,
      "at_jitter": 0.0,
      "at_random_sec": 0.25,
      "buff_group": "",
      "buff_cycle_sec": 0.0,
      "buff_jitter_sec": 0.0,
      "replicatedRow": 0,
      "row_color": ""
    },
    {
      "type": "release",
      "button": "shift",
      "at": 7.04,
      "at_jitter": 0.0,
      "at_random_sec": 0.25,
      "buff_group": "",
      "buff_cycle_sec": 0.0,
      "buff_jitter_sec": 0.0,
      "replicatedRow": 0,
      "row_color": ""
    },
    {
      "type": "press",
      "button": "x",
      "at": 9.78,
      "at_jitter": 0.0,
      "at_random_sec": 0.25,
      "buff_group": "",
      "buff_cycle_sec": 0.0,
      "buff_jitter_sec": 0.0,
      "replicatedRow": 0,
      "row_color": ""
    },
    {
      "type": "release",
      "button": "x",
      "at": 9.83,
      "at_jitter": 0.0,
      "at_random_sec": 0.25,
      "buff_group": "",
      "buff_cycle_sec": 0.0,
      "buff_jitter_sec": 0.0,
      "replicatedRow": 0,
      "row_color": ""
    },
    {
      "type": "press",
      "button": "left",
      "at": 10.84,
      "at_jitter": 0.0,
      "at_random_sec": 0.25,
      "buff_group": "",
      "buff_cycle_sec": 0.0,
      "buff_jitter_sec": 0.0,
      "replicatedRow": 0,
      "row_color": ""
    },
    {
      "type": "release",
      "button": "left",
      "at": 11.51,
      "at_jitter": 0.0,
      "at_random_sec": 0.25,
      "buff_group": "",
      "buff_cycle_sec": 0.0,
      "buff_jitter_sec": 0.0,
      "replicatedRow": 0,
      "row_color": ""
    },
    {
      "type": "press",
      "button": "x",
      "at": 12.0,
      "at_jitter": 0.0,
      "at_random_sec": 0.25,
      "buff_group": "",
      "buff_cycle_sec": 0.0,
      "buff_jitter_sec": 0.0,
      "replicatedRow": 0,
      "row_color": ""
    },
    {
      "type": "release",
      "button": "x",
      "at": 12.34,
      "at_jitter": 0.0,
      "at_random_sec": 0.25,
      "buff_group": "",
      "buff_cycle_sec": 0.0,
      "buff_jitter_sec": 0.0,
      "replicatedRow": 0,
      "row_color": ""
    },
    {
      "type": "press",
      "button": "right",
      "at": 13.48,
      "at_jitter": 0.0,
      "at_random_sec": 0.25,
      "buff_group": "",
      "buff_cycle_sec": 0.0,
      "buff_jitter_sec": 0.0,
      "replicatedRow": 0,
      "row_color": ""
    },
    {
      "type": "release",
      "button": "right",
      "at": 13.57,
      "at_jitter": 0.0,
      "at_random_sec": 0.25,
      "buff_group": "",
      "buff_cycle_sec": 0.0,
      "buff_jitter_sec": 0.0,
      "replicatedRow": 0,
      "row_color": ""
    },
    {
      "type": "press",
      "button": "x",
      "at": 14.02,
      "at_jitter": 0.0,
      "at_random_sec": 0.25,
      "buff_group": "",
      "buff_cycle_sec": 0.0,
      "buff_jitter_sec": 0.0,
      "replicatedRow": 0,
      "row_color": ""
    },
    {
      "type": "release",
      "button": "x",
      "at": 14.16,
      "at_jitter": 0.0,
      "at_random_sec": 0.25,
      "buff_group": "",
      "buff_cycle_sec": 0.0,
      "buff_jitter_sec": 0.0,
      "replicatedRow": 0,
      "row_color": ""
    },
    {
      "type": "press",
      "button": "d",
      "at": 15.7,
      "at_jitter": 0.0,
      "at_random_sec": 0.25,
      "buff_group": "",
      "buff_cycle_sec": 0.0,
      "buff_jitter_sec": 0.0,
      "replicatedRow": 0,
      "row_color": ""
    },
    {
      "type": "release",
      "button": "d",
      "at": 15.82,
      "at_jitter": 0.0,
      "at_random_sec": 0.25,
      "buff_group": "",
      "buff_cycle_sec": 0.0,
      "buff_jitter_sec": 0.0,
      "replicatedRow": 0,
      "row_color": ""
    },
    {
      "type": "press",
      "button": "v",
      "at": 16.66,
      "at_jitter": 0.0,
      "at_random_sec": 0.25,
      "buff_group": "",
      "buff_cycle_sec": 0.0,
      "buff_jitter_sec": 0.0,
      "replicatedRow": 0,
      "row_color": ""
    },
    {
      "type": "release",
      "button": "v",
      "at": 16.9,
      "at_jitter": 0.0,
      "at_random_sec": 0.25,
      "buff_group": "",
      "buff_cycle_sec": 0.0,
      "buff_jitter_sec": 0.0,
      "replicatedRow": 0,
      "row_color": ""
    },
    {
      "type": "press",
      "button": "c",
      "at": 18.64,
      "at_jitter": 0.0,
      "at_random_sec": 0.25,
      "buff_group": "",
      "buff_cycle_sec": 0.0,
      "buff_jitter_sec": 0.0,
      "replicatedRow": 0,
      "row_color": ""
    },
    {
      "type": "release",
      "button": "c",
      "at": 18.85,
      "at_jitter": 0.0,
      "at_random_sec": 0.25,
      "buff_group": "",
      "buff_cycle_sec": 0.0,
      "buff_jitter_sec": 0.0,
      "replicatedRow": 0,
      "row_color": ""
    },
    {
      "type": "press",
      "button": "x",
      "at": 20.5,
      "at_jitter": 0.0,
      "at_random_sec": 0.25,
      "buff_group": "",
      "buff_cycle_sec": 0.0,
      "buff_jitter_sec": 0.0,
      "replicatedRow": 0,
      "row_color": ""
    },
    {
      "type": "release",
      "button": "x",
      "at": 20.67,
      "at_jitter": 0.0,
      "at_random_sec": 0.25,
      "buff_group": "",
      "buff_cycle_sec": 0.0,
      "buff_jitter_sec": 0.0,
      "replicatedRow": 0,
      "row_color": ""
    },
    {
      "type": "press",
      "button": "x",
      "at": 24.29,
      "at_jitter": 0.0,
      "at_random_sec": 0.25,
      "buff_group": "",
      "buff_cycle_sec": 0.0,
      "buff_jitter_sec": 0.0,
      "replicatedRow": 0,
      "row_color": ""
    },
    {
      "type": "release",
      "button": "x",
      "at": 24.34,
      "at_jitter": 0.0,
      "at_random_sec": 0.25,
      "buff_group": "",
      "buff_cycle_sec": 0.0,
      "buff_jitter_sec": 0.0,
      "replicatedRow": 0,
      "row_color": ""
    },
    {
      "type": "press",
      "button": "x",
      "at": 29.41,
      "at_jitter": 0.0,
      "buff_group": "",
      "buff_cycle_sec": 0.0,
      "buff_jitter_sec": 0.0,
      "row_color": "#fff4b3",
      "replicatedRow": 0,
      "at_random_sec": 0.25
    },
    {
      "type": "release",
      "button": "x",
      "at": 29.54,
      "at_jitter": 0.0,
      "buff_group": "",
      "buff_cycle_sec": 0.0,
      "buff_jitter_sec": 0.0,
      "row_color": "#fff4b3",
      "replicatedRow": 0,
      "at_random_sec": 0.25
    },
    {
      "type": "press",
      "button": "x",
      "at": 32.09,
      "at_jitter": 0.0,
      "buff_group": "",
      "buff_cycle_sec": 0.0,
      "buff_jitter_sec": 0.0,
      "row_color": "#fff4b3",
      "replicatedRow": 0,
      "at_random_sec": 0.25
    },
    {
      "type": "release",
      "button": "x",
      "at": 32.32,
      "at_jitter": 0.0,
      "buff_group": "",
      "buff_cycle_sec": 0.0,
      "buff_jitter_sec": 0.0,
      "row_color": "#fff4b3",
      "replicatedRow": 0,
      "at_random_sec": 0.25
    },
    {
      "type": "press",
      "button": "x",
      "at": 33.32,
      "at_jitter": 0.0,
      "buff_group": "-1",
      "buff_cycle_sec": 0.0,
      "buff_jitter_sec": 0.0,
      "row_color": "#fff4b3",
      "replicatedRow": 0,
      "at_random_sec": 0.0
    },
    {
      "type": "release",
      "button": "x",
      "at": 33.4,
      "at_jitter": 0.0,
      "buff_group": "-1",
      "buff_cycle_sec": 0.0,
      "buff_jitter_sec": 0.0,
      "row_color": "#fff4b3",
      "replicatedRow": 0,
      "at_random_sec": 0.0
    },
    {
      "type": "press",
      "button": "x",
      "at": 34.4,
      "at_jitter": 0.0,
      "buff_group": "-3",
      "buff_cycle_sec": 0.0,
      "buff_jitter_sec": 0.0,
      "row_color": "#fff4b3",
      "replicatedRow": 0,
      "at_random_sec": 0.0
    },
    {
      "type": "release",
      "button": "x",
      "at": 34.64,
      "at_jitter": 0.0,
      "buff_group": "-3",
      "buff_cycle_sec": 0.0,
      "buff_jitter_sec": 0.0,
      "row_color": "#fff4b3",
      "replicatedRow": 0,
      "at_random_sec": 0.0
    }
  ],
  "_meta": {
    "original_events": [
      {
        "type": "press",
        "button": "ctrl",
        "at": 3.56,
        "at_jitter": 0.0,
        "at_random_sec": 0.25,
        "buff_group": "",
        "buff_cycle_sec": 0.0,
        "buff_jitter_sec": 0.0,
        "replicatedRow": 0,
        "row_color": ""
      },
      {
        "type": "release",
        "button": "ctrl",
        "at": 3.69,
        "at_jitter": 0.0,
        "at_random_sec": 0.25,
        "buff_group": "",
        "buff_cycle_sec": 0.0,
        "buff_jitter_sec": 0.0,
        "replicatedRow": 0,
        "row_color": ""
      },
      {
        "type": "press",
        "button": "shift",
        "at": 6.73,
        "at_jitter": 0.0,
        "at_random_sec": 0.25,
        "buff_group": "",
        "buff_cycle_sec": 0.0,
        "buff_jitter_sec": 0.0,
        "replicatedRow": 0,
        "row_color": ""
      },
      {
        "type": "release",
        "button": "shift",
        "at": 6.77,
        "at_jitter": 0.0,
        "at_random_sec": 0.25,
        "buff_group": "",
        "buff_cycle_sec": 0.0,
        "buff_jitter_sec": 0.0,
        "replicatedRow": 0,
        "row_color": ""
      },
      {
        "type": "press",
        "button": "shift",
        "at": 6.99,
        "at_jitter": 0.0,
        "at_random_sec": 0.25,
        "buff_group": "",
        "buff_cycle_sec": 0.0,
        "buff_jitter_sec": 0.0,
        "replicatedRow": 0,
        "row_color": ""
      },
      {
        "type": "release",
        "button": "shift",
        "at": 7.04,
        "at_jitter": 0.0,
        "at_random_sec": 0.25,
        "buff_group": "",
        "buff_cycle_sec": 0.0,
        "buff_jitter_sec": 0.0,
        "replicatedRow": 0,
        "row_color": ""
      },
      {
        "type": "press",
        "button": "x",
        "at": 9.78,
        "at_jitter": 0.0,
        "at_random_sec": 0.25,
        "buff_group": "",
        "buff_cycle_sec": 0.0,
        "buff_jitter_sec": 0.0,
        "replicatedRow": 0,
        "row_color": ""
      },
      {
        "type": "release",
        "button": "x",
        "at": 9.83,
        "at_jitter": 0.0,
        "at_random_sec": 0.25,
        "buff_group": "",
        "buff_cycle_sec": 0.0,
        "buff_jitter_sec": 0.0,
        "replicatedRow": 0,
        "row_color": ""
      },
      {
        "type": "press",
        "button": "left",
        "at": 10.84,
        "at_jitter": 0.0,
        "at_random_sec": 0.25,
        "buff_group": "",
        "buff_cycle_sec": 0.0,
        "buff_jitter_sec": 0.0,
        "replicatedRow": 0,
        "row_color": ""
      },
      {
        "type": "release",
        "button": "left",
        "at": 11.51,
        "at_jitter": 0.0,
        "at_random_sec": 0.25,
        "buff_group": "",
        "buff_cycle_sec": 0.0,
        "buff_jitter_sec": 0.0,
        "replicatedRow": 0,
        "row_color": ""
      },
      {
        "type": "press",
        "button": "x",
        "at": 12.0,
        "at_jitter": 0.0,
        "at_random_sec": 0.25,
        "buff_group": "",
        "buff_cycle_sec": 0.0,
        "buff_jitter_sec": 0.0,
        "replicatedRow": 0,
        "row_color": ""
      },
      {
        "type": "release",
        "button": "x",
        "at": 12.34,
        "at_jitter": 0.0,
        "at_random_sec": 0.25,
        "buff_group": "",
        "buff_cycle_sec": 0.0,
        "buff_jitter_sec": 0.0,
        "replicatedRow": 0,
        "row_color": ""
      },
      {
        "type": "press",
        "button": "right",
        "at": 13.48,
        "at_jitter": 0.0,
        "at_random_sec": 0.25,
        "buff_group": "",
        "buff_cycle_sec": 0.0,
        "buff_jitter_sec": 0.0,
        "replicatedRow": 0,
        "row_color": ""
      },
      {
        "type": "release",
        "button": "right",
        "at": 13.57,
        "at_jitter": 0.0,
        "at_random_sec": 0.25,
        "buff_group": "",
        "buff_cycle_sec": 0.0,
        "buff_jitter_sec": 0.0,
        "replicatedRow": 0,
        "row_color": ""
      },
      {
        "type": "press",
        "button": "x",
        "at": 14.02,
        "at_jitter": 0.0,
        "at_random_sec": 0.25,
        "buff_group": "",
        "buff_cycle_sec": 0.0,
        "buff_jitter_sec": 0.0,
        "replicatedRow": 0,
        "row_color": ""
      },
      {
        "type": "release",
        "button": "x",
        "at": 14.16,
        "at_jitter": 0.0,
        "at_random_sec": 0.25,
        "buff_group": "",
        "buff_cycle_sec": 0.0,
        "buff_jitter_sec": 0.0,
        "replicatedRow": 0,
        "row_color": ""
      },
      {
        "type": "press",
        "button": "d",
        "at": 15.7,
        "at_jitter": 0.0,
        "at_random_sec": 0.25,
        "buff_group": "",
        "buff_cycle_sec": 0.0,
        "buff_jitter_sec": 0.0,
        "replicatedRow": 0,
        "row_color": ""
      },
      {
        "type": "release",
        "button": "d",
        "at": 15.82,
        "at_jitter": 0.0,
        "at_random_sec": 0.25,
        "buff_group": "",
        "buff_cycle_sec": 0.0,
        "buff_jitter_sec": 0.0,
        "replicatedRow": 0,
        "row_color": ""
      },
      {
        "type": "press",
        "button": "v",
        "at": 16.66,
        "at_jitter": 0.0,
        "at_random_sec": 0.25,
        "buff_group": "",
        "buff_cycle_sec": 0.0,
        "buff_jitter_sec": 0.0,
        "replicatedRow": 0,
        "row_color": ""
      },
      {
        "type": "release",
        "button": "v",
        "at": 16.9,
        "at_jitter": 0.0,
        "at_random_sec": 0.25,
        "buff_group": "",
        "buff_cycle_sec": 0.0,
        "buff_jitter_sec": 0.0,
        "replicatedRow": 0,
        "row_color": ""
      },
      {
        "type": "press",
        "button": "c",
        "at": 18.64,
        "at_jitter": 0.0,
        "at_random_sec": 0.25,
        "buff_group": "",
        "buff_cycle_sec": 0.0,
        "buff_jitter_sec": 0.0,
        "replicatedRow": 0,
        "row_color": ""
      },
      {
        "type": "release",
        "button": "c",
        "at": 18.85,
        "at_jitter": 0.0,
        "at_random_sec": 0.25,
        "buff_group": "",
        "buff_cycle_sec": 0.0,
        "buff_jitter_sec": 0.0,
        "replicatedRow": 0,
        "row_color": ""
      },
      {
        "type": "press",
        "button": "x",
        "at": 20.5,
        "at_jitter": 0.0,
        "at_random_sec": 0.25,
        "buff_group": "",
        "buff_cycle_sec": 0.0,
        "buff_jitter_sec": 0.0,
        "replicatedRow": 0,
        "row_color": ""
      },
      {
        "type": "release",
        "button": "x",
        "at": 20.67,
        "at_jitter": 0.0,
        "at_random_sec": 0.25,
        "buff_group": "",
        "buff_cycle_sec": 0.0,
        "buff_jitter_sec": 0.0,
        "replicatedRow": 0,
        "row_color": ""
      },
      {
        "type": "press",
        "button": "x",
        "at": 24.29,
        "at_jitter": 0.0,
        "at_random_sec": 0.25,
        "buff_group": "",
        "buff_cycle_sec": 0.0,
        "buff_jitter_sec": 0.0,
        "replicatedRow": 0,
        "row_color": ""
      },
      {
        "type": "release",
        "button": "x",
        "at": 24.34,
        "at_jitter": 0.0,
        "at_random_sec": 0.25,
        "buff_group": "",
        "buff_cycle_sec": 0.0,
        "buff_jitter_sec": 0.0,
        "replicatedRow": 0,
        "row_color": ""
      },
      {
        "type": "press",
        "button": "x",
        "at": 29.41,
        "at_jitter": 0.0,
        "buff_group": "",
        "buff_cycle_sec": 0.0,
        "buff_jitter_sec": 0.0,
        "row_color": "#fff4b3",
        "replicatedRow": 0,
        "at_random_sec": 0.25
      },
      {
        "type": "release",
        "button": "x",
        "at": 29.54,
        "at_jitter": 0.0,
        "buff_group": "",
        "buff_cycle_sec": 0.0,
        "buff_jitter_sec": 0.0,
        "row_color": "#fff4b3",
        "replicatedRow": 0,
        "at_random_sec": 0.25
      },
      {
        "type": "press",
        "button": "x",
        "at": 32.09,
        "at_jitter": 0.0,
        "buff_group": "",
        "buff_cycle_sec": 0.0,
        "buff_jitter_sec": 0.0,
        "row_color": "#fff4b3",
        "replicatedRow": 0,
        "at_random_sec": 0.25
      },
      {
        "type": "release",
        "button": "x",
        "at": 32.32,
        "at_jitter": 0.0,
        "buff_group": "",
        "buff_cycle_sec": 0.0,
        "buff_jitter_sec": 0.0,
        "row_color": "#fff4b3",
        "replicatedRow": 0,
        "at_random_sec": 0.25
      },
      {
        "type": "press",
        "button": "left",
        "at": 33.27,
        "at_jitter": 0.0,
        "buff_group": "",
        "buff_cycle_sec": 0.0,
        "buff_jitter_sec": 0.0,
        "row_color": "#fff4b3",
        "replicatedRow": 0,
        "at_random_sec": 0.25
      },
      {
        "type": "release",
        "button": "left",
        "at": 33.67,
        "at_jitter": 0.0,
        "buff_group": "",
        "buff_cycle_sec": 0.0,
        "buff_jitter_sec": 0.0,
        "row_color": "#fff4b3",
        "replicatedRow": 0,
        "at_random_sec": 0.25
      },
      {
        "type": "press",
        "button": "x",
        "at": 33.97,
        "at_jitter": 0.0,
        "buff_group": "-1",
        "buff_cycle_sec": 0.0,
        "buff_jitter_sec": 0.0,
        "row_color": "#fff4b3",
        "replicatedRow": 0,
        "at_random_sec": 0.0
      },
      {
        "type": "release",
        "button": "x",
        "at": 34.05,
        "at_jitter": 0.0,
        "buff_group": "-1",
        "buff_cycle_sec": 0.0,
        "buff_jitter_sec": 0.0,
        "row_color": "#fff4b3",
        "replicatedRow": 0,
        "at_random_sec": 0.0
      },
      {
        "type": "press",
        "button": "right",
        "at": 34.43,
        "at_jitter": 0.0,
        "buff_group": "-2",
        "buff_cycle_sec": 0.0,
        "buff_jitter_sec": 0.0,
        "row_color": "#fff4b3",
        "replicatedRow": 0,
        "at_random_sec": 0.0
      },
      {
        "type": "release",
        "button": "right",
        "at": 34.57,
        "at_jitter": 0.0,
        "buff_group": "-2",
        "buff_cycle_sec": 0.0,
        "buff_jitter_sec": 0.0,
        "row_color": "#fff4b3",
        "replicatedRow": 0,
        "at_random_sec": 0.0
      },
      {
        "type": "press",
        "button": "x",
        "at": 34.98,
        "at_jitter": 0.0,
        "buff_group": "-3",
        "buff_cycle_sec": 0.0,
        "buff_jitter_sec": 0.0,
        "row_color": "#fff4b3",
        "replicatedRow": 0,
        "at_random_sec": 0.0
      },
      {
        "type": "release",
        "button": "x",
        "at": 35.22,
        "at_jitter": 0.0,
        "buff_group": "-3",
        "buff_cycle_sec": 0.0,
        "buff_jitter_sec": 0.0,
        "row_color": "#fff4b3",
        "replicatedRow": 0,
        "at_random_sec": 0.0
      }
    ],
    "latest_saved_events": [
      {
        "type": "press",
        "button": "ctrl",
        "at": 3.56,
        "at_jitter": 0.0,
        "at_random_sec": 0.25,
        "buff_group": "",
        "buff_cycle_sec": 0.0,
        "buff_jitter_sec": 0.0,
        "replicatedRow": 0,
        "row_color": ""
      },
      {
        "type": "release",
        "button": "ctrl",
        "at": 3.69,
        "at_jitter": 0.0,
        "at_random_sec": 0.25,
        "buff_group": "",
        "buff_cycle_sec": 0.0,
        "buff_jitter_sec": 0.0,
        "replicatedRow": 0,
        "row_color": ""
      },
      {
        "type": "press",
        "button": "shift",
        "at": 6.73,
        "at_jitter": 0.0,
        "at_random_sec": 0.25,
        "buff_group": "",
        "buff_cycle_sec": 0.0,
        "buff_jitter_sec": 0.0,
        "replicatedRow": 0,
        "row_color": ""
      },
      {
        "type": "release",
        "button": "shift",
        "at": 6.77,
        "at_jitter": 0.0,
        "at_random_sec": 0.25,
        "buff_group": "",
        "buff_cycle_sec": 0.0,
        "buff_jitter_sec": 0.0,
        "replicatedRow": 0,
        "row_color": ""
      },
      {
        "type": "press",
        "button": "shift",
        "at": 6.99,
        "at_jitter": 0.0,
        "at_random_sec": 0.25,
        "buff_group": "",
        "buff_cycle_sec": 0.0,
        "buff_jitter_sec": 0.0,
        "replicatedRow": 0,
        "row_color": ""
      },
      {
        "type": "release",
        "button": "shift",
        "at": 7.04,
        "at_jitter": 0.0,
        "at_random_sec": 0.25,
        "buff_group": "",
        "buff_cycle_sec": 0.0,
        "buff_jitter_sec": 0.0,
        "replicatedRow": 0,
        "row_color": ""
      },
      {
        "type": "press",
        "button": "x",
        "at": 9.78,
        "at_jitter": 0.0,
        "at_random_sec": 0.25,
        "buff_group": "",
        "buff_cycle_sec": 0.0,
        "buff_jitter_sec": 0.0,
        "replicatedRow": 0,
        "row_color": ""
      },
      {
        "type": "release",
        "button": "x",
        "at": 9.83,
        "at_jitter": 0.0,
        "at_random_sec": 0.25,
        "buff_group": "",
        "buff_cycle_sec": 0.0,
        "buff_jitter_sec": 0.0,
        "replicatedRow": 0,
        "row_color": ""
      },
      {
        "type": "press",
        "button": "left",
        "at": 10.84,
        "at_jitter": 0.0,
        "at_random_sec": 0.25,
        "buff_group": "",
        "buff_cycle_sec": 0.0,
        "buff_jitter_sec": 0.0,
        "replicatedRow": 0,
        "row_color": ""
      },
      {
        "type": "release",
        "button": "left",
        "at": 11.51,
        "at_jitter": 0.0,
        "at_random_sec": 0.25,
        "buff_group": "",
        "buff_cycle_sec": 0.0,
        "buff_jitter_sec": 0.0,
        "replicatedRow": 0,
        "row_color": ""
      },
      {
        "type": "press",
        "button": "x",
        "at": 12.0,
        "at_jitter": 0.0,
        "at_random_sec": 0.25,
        "buff_group": "",
        "buff_cycle_sec": 0.0,
        "buff_jitter_sec": 0.0,
        "replicatedRow": 0,
        "row_color": ""
      },
      {
        "type": "release",
        "button": "x",
        "at": 12.34,
        "at_jitter": 0.0,
        "at_random_sec": 0.25,
        "buff_group": "",
        "buff_cycle_sec": 0.0,
        "buff_jitter_sec": 0.0,
        "replicatedRow": 0,
        "row_color": ""
      },
      {
        "type": "press",
        "button": "right",
        "at": 13.48,
        "at_jitter": 0.0,
        "at_random_sec": 0.25,
        "buff_group": "",
        "buff_cycle_sec": 0.0,
        "buff_jitter_sec": 0.0,
        "replicatedRow": 0,
        "row_color": ""
      },
      {
        "type": "release",
        "button": "right",
        "at": 13.57,
        "at_jitter": 0.0,
        "at_random_sec": 0.25,
        "buff_group": "",
        "buff_cycle_sec": 0.0,
        "buff_jitter_sec": 0.0,
        "replicatedRow": 0,
        "row_color": ""
      },
      {
        "type": "press",
        "button": "x",
        "at": 14.02,
        "at_jitter": 0.0,
        "at_random_sec": 0.25,
        "buff_group": "",
        "buff_cycle_sec": 0.0,
        "buff_jitter_sec": 0.0,
        "replicatedRow": 0,
        "row_color": ""
      },
      {
        "type": "release",
        "button": "x",
        "at": 14.16,
        "at_jitter": 0.0,
        "at_random_sec": 0.25,
        "buff_group": "",
        "buff_cycle_sec": 0.0,
        "buff_jitter_sec": 0.0,
        "replicatedRow": 0,
        "row_color": ""
      },
      {
        "type": "press",
        "button": "d",
        "at": 15.7,
        "at_jitter": 0.0,
        "at_random_sec": 0.25,
        "buff_group": "",
        "buff_cycle_sec": 0.0,
        "buff_jitter_sec": 0.0,
        "replicatedRow": 0,
        "row_color": ""
      },
      {
        "type": "release",
        "button": "d",
        "at": 15.82,
        "at_jitter": 0.0,
        "at_random_sec": 0.25,
        "buff_group": "",
        "buff_cycle_sec": 0.0,
        "buff_jitter_sec": 0.0,
        "replicatedRow": 0,
        "row_color": ""
      },
      {
        "type": "press",
        "button": "v",
        "at": 16.66,
        "at_jitter": 0.0,
        "at_random_sec": 0.25,
        "buff_group": "",
        "buff_cycle_sec": 0.0,
        "buff_jitter_sec": 0.0,
        "replicatedRow": 0,
        "row_color": ""
      },
      {
        "type": "release",
        "button": "v",
        "at": 16.9,
        "at_jitter": 0.0,
        "at_random_sec": 0.25,
        "buff_group": "",
        "buff_cycle_sec": 0.0,
        "buff_jitter_sec": 0.0,
        "replicatedRow": 0,
        "row_color": ""
      },
      {
        "type": "press",
        "button": "c",
        "at": 18.64,
        "at_jitter": 0.0,
        "at_random_sec": 0.25,
        "buff_group": "",
        "buff_cycle_sec": 0.0,
        "buff_jitter_sec": 0.0,
        "replicatedRow": 0,
        "row_color": ""
      },
      {
        "type": "release",
        "button": "c",
        "at": 18.85,
        "at_jitter": 0.0,
        "at_random_sec": 0.25,
        "buff_group": "",
        "buff_cycle_sec": 0.0,
        "buff_jitter_sec": 0.0,
        "replicatedRow": 0,
        "row_color": ""
      },
      {
        "type": "press",
        "button": "x",
        "at": 20.5,
        "at_jitter": 0.0,
        "at_random_sec": 0.25,
        "buff_group": "",
        "buff_cycle_sec": 0.0,
        "buff_jitter_sec": 0.0,
        "replicatedRow": 0,
        "row_color": ""
      },
      {
        "type": "release",
        "button": "x",
        "at": 20.67,
        "at_jitter": 0.0,
        "at_random_sec": 0.25,
        "buff_group": "",
        "buff_cycle_sec": 0.0,
        "buff_jitter_sec": 0.0,
        "replicatedRow": 0,
        "row_color": ""
      },
      {
        "type": "press",
        "button": "x",
        "at": 24.29,
        "at_jitter": 0.0,
        "at_random_sec": 0.25,
        "buff_group": "",
        "buff_cycle_sec": 0.0,
        "buff_jitter_sec": 0.0,
        "replicatedRow": 0,
        "row_color": ""
      },
      {
        "type": "release",
        "button": "x",
        "at": 24.34,
        "at_jitter": 0.0,
        "at_random_sec": 0.25,
        "buff_group": "",
        "buff_cycle_sec": 0.0,
        "buff_jitter_sec": 0.0,
        "replicatedRow": 0,
        "row_color": ""
      },
      {
        "type": "press",
        "button": "x",
        "at": 29.41,
        "at_jitter": 0.0,
        "buff_group": "",
        "buff_cycle_sec": 0.0,
        "buff_jitter_sec": 0.0,
        "row_color": "#fff4b3",
        "replicatedRow": 0,
        "at_random_sec": 0.25
      },
      {
        "type": "release",
        "button": "x",
        "at": 29.54,
        "at_jitter": 0.0,
        "buff_group": "",
        "buff_cycle_sec": 0.0,
        "buff_jitter_sec": 0.0,
        "row_color": "#fff4b3",
        "replicatedRow": 0,
        "at_random_sec": 0.25
      },
      {
        "type": "press",
        "button": "x",
        "at": 32.09,
        "at_jitter": 0.0,
        "buff_group": "",
        "buff_cycle_sec": 0.0,
        "buff_jitter_sec": 0.0,
        "row_color": "#fff4b3",
        "replicatedRow": 0,
        "at_random_sec": 0.25
      },
      {
        "type": "release",
        "button": "x",
        "at": 32.32,
        "at_jitter": 0.0,
        "buff_group": "",
        "buff_cycle_sec": 0.0,
        "buff_jitter_sec": 0.0,
        "row_color": "#fff4b3",
        "replicatedRow": 0,
        "at_random_sec": 0.25
      },
      {
        "type": "press",
        "button": "x",
        "at": 33.32,
        "at_jitter": 0.0,
        "buff_group": "-1",
        "buff_cycle_sec": 0.0,
        "buff_jitter_sec": 0.0,
        "row_color": "#fff4b3",
        "replicatedRow": 0,
        "at_random_sec": 0.0
      },
      {
        "type": "release",
        "button": "x",
        "at": 33.4,
        "at_jitter": 0.0,
        "buff_group": "-1",
        "buff_cycle_sec": 0.0,
        "buff_jitter_sec": 0.0,
        "row_color": "#fff4b3",
        "replicatedRow": 0,
        "at_random_sec": 0.0
      },
      {
        "type": "press",
        "button": "x",
        "at": 34.4,
        "at_jitter": 0.0,
        "buff_group": "-3",
        "buff_cycle_sec": 0.0,
        "buff_jitter_sec": 0.0,
        "row_color": "#fff4b3",
        "replicatedRow": 0,
        "at_random_sec": 0.0
      },
      {
        "type": "release",
        "button": "x",
        "at": 34.64,
        "at_jitter": 0.0,
        "buff_group": "-3",
        "buff_cycle_sec": 0.0,
        "buff_jitter_sec": 0.0,
        "row_color": "#fff4b3",
        "replicatedRow": 0,
        "at_random_sec": 0.0
      }
    ]
  }
}